setup.py
PyWorker.egg-info/PKG-INFO
PyWorker.egg-info/SOURCES.txt
PyWorker.egg-info/dependency_links.txt
PyWorker.egg-info/requires.txt
PyWorker.egg-info/top_level.txt
pyworker/__init__.py
pyworker/httpworker.py
pyworker/jsonworker.py
pyworker/pyworker.py