Metadata-Version: 1.0
Name: PyWorker
Version: 0.2.3
Summary: PyWorker - Worker classes for performing queued tasks
Home-page: UNKNOWN
Author: Ben O'Steen
Author-email: bosteen@gmail.com
License: UNKNOWN
Platform: UNKNOWN
